diadump/__init__.py
diadump/cli.py
diadump/dumper.py
diadump-0.2.0.dist-info/DESCRIPTION.rst
diadump-0.2.0.dist-info/METADATA
diadump-0.2.0.dist-info/RECORD
diadump-0.2.0.dist-info/WHEEL
diadump-0.2.0.dist-info/entry_points.txt
diadump-0.2.0.dist-info/metadata.json
diadump-0.2.0.dist-info/top_level.txt
